NumpyHePandasShujufenxiShiyongZhinanChuyi/README.md
NumpyHePandasShujufenxiShiyongZhinanChuyi/__init__.py
NumpyHePandasShujufenxiShiyongZhinanChuyi/__main__.py
NumpyHePandasShujufenxiShiyongZhinanChuyi/file.epub
NumpyHePandasShujufenxiShiyongZhinanChuyi/index.html
NumpyHePandasShujufenxiShiyongZhinanChuyi/css/__init__.py
NumpyHePandasShujufenxiShiyongZhinanChuyi/css/annotations.css
NumpyHePandasShujufenxiShiyongZhinanChuyi/css/main.css
NumpyHePandasShujufenxiShiyongZhinanChuyi/css/normalize.css
NumpyHePandasShujufenxiShiyongZhinanChuyi/css/popup.css
NumpyHePandasShujufenxiShiyongZhinanChuyi/font/__init__.py
NumpyHePandasShujufenxiShiyongZhinanChuyi/font/fontello.eot
NumpyHePandasShujufenxiShiyongZhinanChuyi/font/fontello.svg
NumpyHePandasShujufenxiShiyongZhinanChuyi/font/fontello.ttf
NumpyHePandasShujufenxiShiyongZhinanChuyi/font/fontello.woff
NumpyHePandasShujufenxiShiyongZhinanChuyi/img/__init__.py
NumpyHePandasShujufenxiShiyongZhinanChuyi/img/annotator-glyph-sprite.png
NumpyHePandasShujufenxiShiyongZhinanChuyi/img/annotator-icon-sprite.png
NumpyHePandasShujufenxiShiyongZhinanChuyi/img/apple-touch-icon.png
NumpyHePandasShujufenxiShiyongZhinanChuyi/img/cancelfullscreen.png
NumpyHePandasShujufenxiShiyongZhinanChuyi/img/close.png
NumpyHePandasShujufenxiShiyongZhinanChuyi/img/fullscreen.png
NumpyHePandasShujufenxiShiyongZhinanChuyi/img/loader.gif
NumpyHePandasShujufenxiShiyongZhinanChuyi/img/menu-icon.png
NumpyHePandasShujufenxiShiyongZhinanChuyi/img/save.png
NumpyHePandasShujufenxiShiyongZhinanChuyi/img/saved.png
NumpyHePandasShujufenxiShiyongZhinanChuyi/img/settings-s.png
NumpyHePandasShujufenxiShiyongZhinanChuyi/img/settings.png
NumpyHePandasShujufenxiShiyongZhinanChuyi/img/star.png
NumpyHePandasShujufenxiShiyongZhinanChuyi/js/__init__.py
NumpyHePandasShujufenxiShiyongZhinanChuyi/js/epub.js
NumpyHePandasShujufenxiShiyongZhinanChuyi/js/epub.min.js
NumpyHePandasShujufenxiShiyongZhinanChuyi/js/epub.min.map
NumpyHePandasShujufenxiShiyongZhinanChuyi/js/hooks.min.js
numpy_he_pandas_shujufenxi_shiyong_zhinan_chuyi-2024.3.5.0.dist-info/METADATA
numpy_he_pandas_shujufenxi_shiyong_zhinan_chuyi-2024.3.5.0.dist-info/WHEEL
numpy_he_pandas_shujufenxi_shiyong_zhinan_chuyi-2024.3.5.0.dist-info/entry_points.txt
numpy_he_pandas_shujufenxi_shiyong_zhinan_chuyi-2024.3.5.0.dist-info/top_level.txt
numpy_he_pandas_shujufenxi_shiyong_zhinan_chuyi-2024.3.5.0.dist-info/RECORD
